bytedance_forest/__init__.py
bytedance_forest-0.0.1.dist-info/METADATA
bytedance_forest-0.0.1.dist-info/WHEEL
bytedance_forest-0.0.1.dist-info/top_level.txt
bytedance_forest-0.0.1.dist-info/RECORD
